nifti_converter/__init__.py
nifti_converter/iseq2nii.py
nifti_converter/nii2iseq.py
nifti_converter-0.1.0.dist-info/METADATA
nifti_converter-0.1.0.dist-info/WHEEL
nifti_converter-0.1.0.dist-info/entry_points.txt
nifti_converter-0.1.0.dist-info/licenses/LICENSE
nifti_converter-0.1.0.dist-info/RECORD
