Metadata-Version: 2.3
Name: nifti-converter
Version: 0.1.0
Summary: Convert NIfTI files to usual image formats
Project-URL: Repository, https://github.com/neurodata-tokyo/nifti-converter
Author-email: "Neurodata.tokyo" <contact@neurodata.tokyo>
License-File: LICENSE
Keywords: image,nifti,nii
Classifier: Development Status :: 3 - Alpha
Classifier: Environment :: Console
Classifier: Intended Audience :: Science/Research
Classifier: License :: OSI Approved :: MIT License
Classifier: Operating System :: OS Independent
Classifier: Programming Language :: Python
Classifier: Programming Language :: Python :: 3 :: Only
Classifier: Programming Language :: Python :: 3.11
Classifier: Programming Language :: Python :: 3.12
Classifier: Programming Language :: Python :: 3.13
Classifier: Topic :: Scientific/Engineering :: Bio-Informatics
Classifier: Topic :: Scientific/Engineering :: Image Processing
Requires-Python: >=3.11
Requires-Dist: nibabel>=5.2.1
Requires-Dist: numpy>=2.1.1
Requires-Dist: pillow>=10.4.0
Requires-Dist: typer>=0.12.5
